heat_infoblox/__init__.py
heat_infoblox/config.py
heat_infoblox/connector.py
heat_infoblox/constants.py
heat_infoblox/ibexceptions.py
heat_infoblox/netmri_resource_mixin.py
heat_infoblox/object_manipulator.py
heat_infoblox/resource_utils.py
heat_infoblox/resources/__init__.py
heat_infoblox/resources/anycast_loopback.py
heat_infoblox/resources/bgp.py
heat_infoblox/resources/bgp_neighbor.py
heat_infoblox/resources/grid_member.py
heat_infoblox/resources/ha_pair.py
heat_infoblox/resources/nameserver_group_member.py
heat_infoblox/resources/netmri_job.py
heat_infoblox/resources/netmri_managed_resource.py
heat_infoblox/resources/ospf.py
heat_infoblox/tests/__init__.py
heat_infoblox/tests/test_bgp.py
heat_infoblox/tests/test_bgp_neighbor.py
heat_infoblox/tests/test_grid_member.py
heat_infoblox/tests/test_ha_pair.py
heat_infoblox/tests/test_nameserver_group_member.py
heat_infoblox/tests/test_object_manipulator.py
heat_infoblox/tests/test_ospf.py
heat_infoblox/tests/test_resource_utils.py
heat_infoblox/tests/utils.py
heat_infoblox-2.0.0.dist-info/DESCRIPTION.rst
heat_infoblox-2.0.0.dist-info/METADATA
heat_infoblox-2.0.0.dist-info/RECORD
heat_infoblox-2.0.0.dist-info/WHEEL
heat_infoblox-2.0.0.dist-info/metadata.json
heat_infoblox-2.0.0.dist-info/pbr.json
heat_infoblox-2.0.0.dist-info/top_level.txt
