Metadata-Version: 2.0
Name: heat-infoblox
Version: 2.0.0
Summary: OpenStack Heat resources for orchestrating Infoblox appliances.
Home-page: http://www.infoblox.com/
Author: Infoblox, Inc.
Author-email: openstack-maintainer@infoblox.com
License: UNKNOWN
Platform: UNKNOWN
Classifier: Environment :: OpenStack
Classifier: Intended Audience :: Information Technology
Classifier: Intended Audience :: System Administrators
Classifier: License :: OSI Approved :: Apache Software License
Classifier: Operating System :: POSIX :: Linux
Classifier: Programming Language :: Python
Classifier: Programming Language :: Python :: 2
Classifier: Programming Language :: Python :: 2.7
Requires-Dist: Babel (!=2.3.2,>=1.3,!=2.3.1,!=2.3.3,!=2.3.0)
Requires-Dist: infoblox-netmri (>=0.1.3)
Requires-Dist: oslo.concurrency (>=2.3.0)
Requires-Dist: oslo.config (>=2.3.0)
Requires-Dist: pbr (>=1.6)
